MANIFEST.in
README.rst
hared.ini
setup.py
bin/hared
hared/__init__.py
hared.egg-info/PKG-INFO
hared.egg-info/SOURCES.txt
hared.egg-info/dependency_links.txt
hared.egg-info/not-zip-safe
hared.egg-info/requires.txt
hared.egg-info/top_level.txt