Metadata-Version: 1.0
Name: hared
Version: 1.0
Summary: hare daemon
Home-page: https://jpmens.net/2018/03/25/alerting-on-ssh-logins/
Author: Jan-Piet Mens
Author-email: jp@mens.de
License: MIT
Keywords: UDP MQTT daemon PAM login SSH
Platform: UNKNOWN
